sphinxcontrib_dartdomain-0.1.0-py3.10-nspkg.pth
sphinxcontrib/dartdomain.py
sphinxcontrib_dartdomain-0.1.0.dist-info/LICENSE
sphinxcontrib_dartdomain-0.1.0.dist-info/METADATA
sphinxcontrib_dartdomain-0.1.0.dist-info/WHEEL
sphinxcontrib_dartdomain-0.1.0.dist-info/namespace_packages.txt
sphinxcontrib_dartdomain-0.1.0.dist-info/top_level.txt
sphinxcontrib_dartdomain-0.1.0.dist-info/RECORD
