Metadata-Version: 2.1
Name: sphinxcontrib-dartdomain
Version: 0.1.0
Summary: Sphinx "dartdomain" extension
Home-page: http://github.com/danhunsaker/sphinxcontrib-dartdomain
Download-URL: http://pypi.python.org/pypi/sphinxcontrib-dartdomain
Author: Hennik Hunsaker
Author-email: hennik@insidiouslogic.systems
License: BSD
Platform: any
Classifier: Development Status :: 4 - Beta
Classifier: Environment :: Console
Classifier: Environment :: Web Environment
Classifier: Framework :: Sphinx :: Extension
Classifier: Intended Audience :: Developers
Classifier: License :: OSI Approved :: BSD License
Classifier: Operating System :: OS Independent
Classifier: Programming Language :: Python
Classifier: Topic :: Documentation
Classifier: Topic :: Utilities
License-File: LICENSE
Requires-Dist: Sphinx (>=1.0)
